portablemc_archives/__init__.py
portablemc_archives-2.0.0.dist-info/WHEEL
portablemc_archives-2.0.0.dist-info/METADATA
portablemc_archives-2.0.0.dist-info/RECORD
